kaiostocks/__init__.py
kaiostocks/stocks_bot.py
kaiostocks-0.0.8.dist-info/METADATA
kaiostocks-0.0.8.dist-info/WHEEL
kaiostocks-0.0.8.dist-info/top_level.txt
kaiostocks-0.0.8.dist-info/RECORD
